extra_redu/__init__.py
extra_redu/_version.py
extra_redu/base/__init__.py
extra_redu/base/bunches.py
extra_redu/base/litfrm.py
extra_redu/fileutils/__init__.py
extra_redu/fileutils/datafile.py
extra_redu/fileutils/h5utils.py
extra_redu/fileutils/misc.py
extra_redu/fileutils/pulse_source.py
extra_redu/fileutils/stacking.py
extra_redu/fileutils/writer.py
extra_redu/fileutils/tests/__init__.py
extra_redu/fileutils/tests/test_datafile.py
extra_redu/fileutils/tests/test_h5utils.py
extra_redu/fileutils/tests/test_misc.py
extra_redu/fileutils/tests/test_stacking.py
extra_redu/fileutils/tests/test_writer.py
extra_redu/fileutils/tests/mock/__init__.py
extra_redu/fileutils/tests/mock/datafile.py
extra_redu/fileutils/tests/mock/extra_data.py
extra_redu/fileutils/tests/mock/h5py.py
extra_redu/litfrm/__init__.py
extra_redu/litfrm/agipd_offline.py
extra_redu/litfrm/exdf_reduce.py
extra_redu/litfrm/litfrm_report.py
extra_redu/litfrm/selection.py
extra_redu/litfrm/utils.py
extra_redu/litfrm/draw/__init__.py
extra_redu/litfrm/draw/agipd.py
extra_redu/litfrm/tests/test_litfrm_agipd.py
extra_redu/lossy/__init__.py
extra_redu/lossy/crounding.pxd
extra_redu/lossy/rounding.cpython-310-x86_64-linux-gnu.so
extra_redu/lossy/rounding.h
extra_redu/lossy/rounding.pyx
extra_redu/lossy/rounding_impl.c
extra_redu/lossy/tests/test_rounding.py
extra_redu/spi/__init__.py
extra_redu/spi/hitfinder.py
extra_redu/spi/hitfinding.py
extra_redu/spi/hitfinding_report.ipynb
extra_redu/spi/litpxcounter.py
extra_redu/spi/tests/__init__.py
extra_redu/spi/tests/conftest.py
extra_redu/spi/tests/test_hitfinder.py
extra_redu/spi/tests/test_hitfinding_script.py
extra_redu/spi/tests/test_litpx_counter.py
extra_redu/spi/tests/mock/agipd.py
extra_redu/spi/tests/mock/models.py
extra_redu-1.0.2.dist-info/METADATA
extra_redu-1.0.2.dist-info/WHEEL
extra_redu-1.0.2.dist-info/entry_points.txt
extra_redu-1.0.2.dist-info/top_level.txt
extra_redu-1.0.2.dist-info/RECORD
extra_redu-1.0.2.dist-info/licenses/LICENSE
